{
    "更新日期": "2014\/11\/13 下午 04:35:00",
    "學校代碼": "114525",
    "中文名稱": "市立學甲國民中學",
    "英文名稱": "Tainan Municipal Syuejia Junior High School",
    "建校日期": "45年8月",
    "註記": "正常",
    "學校地址": "726臺南市學甲區新達里6鄰華宗路540號",
    "學校網址": "http:\/\/www.sjjh.tn.edu.tw",
    "校長": "",
    "學校電話": {
        "學校電話": "7832128",
        "傳真一": "7820917",
        "校長室": "7837771  [校長]網路電話：118001",
        "教務處": "7831656網路電話：118010",
        "訓導處": "7834123網路電話：118020",
        "總務處": "7833217網路電話：118040",
        "輔導室": "7820419網路電話：118030",
        "人事室": "7832128#219網路電話：118051",
        "主計室": "7832128#218網路電話：118050"
    },
    "教職員數": {
        "total": 68,
        "代理代課教師": 9,
        "正式教師": 47,
        "替代役男": 1,
        "正式職員工": 8,
        "工友": 3,
        "其他": 0,
        "專長教師": 0
    },
    "學生人數": {
        "total": 539,
        "男": "281",
        "女": "258"
    },
    "年級班數": {
        "total": 24,
        "國中一年級": 8,
        "國中二年級": 8,
        "國中三年級": 8
    },
    "特殊班級數": {
        "total": 2,
        "資源班": 1,
        "啟智班": 1
    },
    "學 區": "學甲區",
    "校舍校地面積": {
        "校地總面積": "48745平方公尺",
        "校舍總延面積": "16028平方公尺",
        "建坪面積": "4882平方公尺"
    },
    "歲出結算數": {
        "資本門支出": "190347元",
        "經常門支出": "106832056元"
    },
    "校長辦學理念": "一.現今教育思潮的主流是以 \"人\" 為教育的主體，也是台灣目前教育改革的訴\r\n求重點。\r\n二.「全人教育」是促進全人發展的教育，它是以人性化的教育為目標；以肯定\r\n人性的尊嚴為基點；以發揮人性的潛能為理想。目的在尊重人的價值，發展人的特質，最後促進其自我實現。\r\n三.新學校.新風格.新觀念.新作風，本校在創立之初，即倡導實施全人教育。\r\n教務方面：改進教學方法，提昇教學品質，使學生快快樂樂的學習。",
    "學校特色": "教務方面：改進教學方法，提昇教學品質，使學生快快樂樂的學習。\r\n1.現代化的教學設備，提高學習興趣：具有特色的各類專科教室，提供學生開放式的彈性空間。\r\n2.充分發揮教師專業自主權，落實校園民主：教師專業化的教學，提供學生有\r\n效能的學習。\r\n3.實施戶外教學，拓展學生學習領域：利用校外資源，規劃各類學習活動，豐\r\n富學習的內容。\r\n4.重視教學研究，改進教學方法：舉辦各科教學研究會，激勵教師專業的服務\r\n熱忱。\r\n5.舉辦各項學藝競賽，學習多樣化。\r\n（二）訓輔方面：落實訓輔合一，使學生身心健全發展。\r\n1.實施人性化的訓輔制度：以輔導代替訓導，尊重人的價值，實現了教育的大\r\n愛。\r\n2.落實導師責任制：和諧的師生關係，營造了溫馨的校園倫理。\r\n3.注重生活教育，強調 \"教育即生活\" ，教導學生學習生活.學習如何學習，\r\n並且能以主動.積極.負責的態度去面對生活。\r\n4.舉辦多樣化的學生活動，成立各類社團活動，排球隊.宋江金獅陣.扯鈴.\r\n合唱團等，\"人盡其才\" . \"適性發展\" ，使學生的潛能充分發揮，才能適性表現，不但調和了個性與群性的發展，也創造了多采多姿的學校生活。\r\n5.召開學生幹部自治座談會：能培養學生獨立思考及自我表達的能力，及提升\r\n民主素養與法治精神。\r\n（三）總務方面：規劃適切的校園環境，發揮境教功能，變化學生氣質。\r\n1.無障礙的校園環境，彈性開放師生活動空間：透明化的圍牆.雙面走廊.風\r\n雨教室的設計，均能展現本校開明.民主的校園風格。\r\n2.美化綠化的校園景觀設計：能營造一個舒適的學習環境，培養怡情悅性的全\r\n人格發展。\r\n3.高品質的中央飲水系統：徹底過濾殺菌，提供高品質的飲用水，確保學生飲\r\n用水的衛生及安全。\r\n4.提昇教學品質，增進教學效果的學校建設，分為動態區與靜態區分隔，專科\r\n教室與普通教室遠離，不致相互干擾。\r\n5.實施公物認管制度：培養學生公德心.責任心與愛校心，凝聚「生命共同體」\r\n的理念。",
    "大事紀": "99學年度重要績效\r\n1.柯瑜婷老師.黃子銘老師指導學生鄭玉琳.侯佳瑩.陳冠輔.王亮欽參加臺\r\n南縣99年度國民中小學科學展覽會榮獲生物科佳作。\r\n2.陳炳宏主任參加台南縣九十九年度自由軟體融入教學創意競賽『潟湖生態系』作品\r\n榮獲國中組優等。\r\n3.張家豪老師.黃子銘老師榮獲99年度攜手計畫課後扶助第一次輔導訪視績優教師。\r\n4.莊蕙嫚老師指導學生參加臺南縣99年度「閩.客.原」本土文化教學書籤創作競賽。\r\n學生何念欣榮獲原語國中組第二名；學生王欣嵐榮獲客語國中組第一名。\r\n5.台南縣99年度推動品德教育績優學校審查，榮獲甲等。\r\n6.參加2010年全國宋江陣暨南瀛盃龍獅藝陣錦標賽，技藝精湛榮獲國中組宋江\r\n金獅陣第一名。\r\n7.台南縣99學年度全縣音樂比賽，榮獲國中女生合唱團體甲組B組甲等。\r\n8.參加99年第37屆永信盃全國排球錦標賽，榮獲國男組第三名。\r\n9.參加99年第31屆華宗盃全國排球錦標賽，榮獲國男組第四名。\r\n10.99年台南縣「有愛無礙」特教學生才藝比賽國中組團體賽第三名。\r\n11.99年度台南縣友善校園3Q達人評選活動AQ達人第三名-陳姿蓉，EQ達人-\r\n第三名曾敏兒。\r\n12.台南縣99學年度全縣音樂比賽，榮獲國中女生合唱團體甲組B組甲等。\r\n13.參加99年第37屆永信盃全國排球錦標賽，榮獲國男組第三名。\r\n14.參加99年第31屆華宗盃全國排球錦標賽，榮獲國男組第四名。\r\n15.參加100年第55屆和家盃全國排球錦標賽，榮獲國男組第四名。\r\n16.參加100年莒光盃全國排球錦標賽，榮獲國男組第三名。\r\n17.學生個人比賽\r\n（1）二年三班 陳奕君\r\n     a. 台南縣99年全縣聯合運動會國武術—南拳社女組第一名\r\n     b. 2010年全國宋江陣暨南瀛盃龍獅藝陣錦標賽—國女組拳術第一名\r\n     c. 2010國際少林武術大賽暨九十九年全國中正盃少林拳道武術錦標賽傳統國術\r\n傳統外家南拳青少年B女第五名\r\n     d. 2010南都武術錦標賽 國女組 第一名\r\n（2）二年七班陳正沛\r\n     a. 台南縣99年全縣聯合運動會國武術—北派拳術第三名\r\n     b. 台南縣99年全縣聯合運動會國武術—短兵 第四名\r\n     c. 2010南都武術錦標賽 國男組甲等南拳第一名\r\n     d. 2010南都武術錦標賽 國男組 傳統劍術 第一名\r\n     e. 2010南都武術錦標賽 國男組 傳統北拳 第一名\r\n     f. 台南縣99學年度學生舞蹈比賽 國中個人組 民俗舞 優等第二\r\n     g. 台南縣99學年度學生舞蹈比賽 國中個人組 古典舞 優等第三\r\n（3）二年四班許儷錦\r\n     臺南縣地層下陷防治海報宣導比賽  佳作\r\n18.100年臺南市中等學校運動會\r\n  （1）莊喻筑榮獲55公斤級國女組跆拳道第一名\r\n  （2）王任哲榮獲78公斤級國男組跆拳道第二名\r\n  （3）陳聖憲榮獲78公斤級國男組跆拳道第五名\r\n  （4）丁柏均榮獲55公斤級國男組跆拳道第五名\r\n  （5）賴俊儒榮獲66公斤級國男組跆拳道第五名\r\n  （6）謝宜庭榮獲田徑---鉛球國女組第五名\r\n  （7）郭郁君榮獲田徑---跳遠國女組第八名\r\n19.2010年台南縣「有愛無礙」特教學生才藝比賽團體組第三名",
    "校務未來發展重點": "總而言之，教學為先.學生第一是我們的教育理念，時時想到學生，處處照顧老師是我們的行政理念。本校倡導實施全人教育，推展以全人教育為主軸的校務行政，期望能以開放的精神.人文的情懷.尊重的態度及民主的素養，培育出二十一世紀身心健全發展的現代化國民，塑造「學生快樂學習.教師尊嚴教學.家長信任參與」的學校。"
}