{
    "更新日期": "2014\/9\/23 下午 02:10:00",
    "學校代碼": "213629",
    "中文名稱": "臺南市安南區安慶國民小學",
    "英文名稱": "AN-CING  ELEMENTARY SCHOOL",
    "建校日期": "1983",
    "註記": "正常",
    "學校地址": "709台南市安南區梅花里17鄰安中路一段七O三巷八O號",
    "學校網址": "http:\/\/www.aces.tn.edu.tw",
    "校長": "黃俊傑",
    "學校電話": {
        "學校電話": "2460334",
        "傳真一": "2475032",
        "校長室": "2460334#1801  [黃俊傑校長]網路電話：43001",
        "教務處": "2460334#1701  [嚴億婷主任]網路電話：43010",
        "訓導處": "2460334#1704  [黃儒賢主任]網路電話：43020",
        "總務處": "2460334#1707  [蘇振輝主任]網路電話：43040",
        "輔導室": "2460334#1810  [張瑞隆主任]網路電話：43030",
        "人事室": "2460334#1806  [詹莉莉主任]網路電話：43051",
        "主計室": "2460334#1805  [陳碧蓮主任]網路電話：43050"
    },
    "教職員數": {
        "total": 135,
        "正式職員工": 10,
        "正式教師": 88,
        "代理代課教師": 27,
        "實習教師": 5,
        "臨時約僱": 4,
        "替代役男": 1
    },
    "學生人數": {
        "total": 1402,
        "男": "731",
        "女": "671"
    },
    "年級班數": {
        "total": 58,
        "一年級": 9,
        "二年級": 8,
        "三年級": 10,
        "四年級": 9,
        "五年級": 10,
        "六年級": 9,
        "幼稚園": 3
    },
    "特殊班級數": {
        "total": 7,
        "啟智班": 4,
        "資源班": 2,
        "學前特教巡迴輔導班": 1
    },
    "學 區": "◎梅花里、鳳凰里、理想里、大安里全部鄰別◎海東里（6.17.22.23.24鄰）為本校學區，（18至21鄰為與海東國小共同學區）◎頂安里（安慶、安順共同學區）◎安慶里（12.14至26鄰）為安慶、安順共同學區， 其餘為安順國小學區◎原佃里（安慶、長安共同學區）",
    "校舍校地面積": {
        "校地總面積": "29567.12平方公尺",
        "校舍總延面積": "19978.92平方公尺",
        "建坪面積": "17408.53平方公尺"
    },
    "歲出結算數": {
        "資本門支出": "879760元",
        "經常門支出": "139337780元"
    },
    "校長辦學理念": "1.          開展學生潛能，提供成功機會：培養學生具備批判思考、主動學習、解決問題、自我行銷、生活知能的能力，並形塑學生誠實、尊重、負責、感恩、關懷的品格。幫助學生迎接健康、快樂、和諧的未來，幫助家長和老師找到對孩子的「教育良方」。\r\n2.          塑造和諧民主、人文關懷的校園文化：建構一個以「孩子即學校主體」的學習樂園，提供安全、人性化的學習環境，使兒童喜歡上學，樂於學習。以「愛與榜樣」為核心理念，全人教育為目標，追求卓越、安全、溫馨活力的校園。\r\n3.          追求精緻卓越，增進服務績效：本著服務的理念，以民主參與的方式，結合教師同仁與家長的力量，營造溫馨祥和的校園環境與快樂積極的學習氣氛，共謀學校教育的進步與發展。\r\n4.          協助教師成長，活化教師專業：組織教師成長團隊，建立學習型組織，透過教學專業對話，思考教育問題，提升教學品質。鼓勵教師自我期許與自我實現，擁有開放的胸襟，勇於學習新事物，接納新理念。",
    "學校特色": "學校特色：\r\n\r\n積極推動資訊融入各科教學，增進師生資訊素養與技能，使學生樂於學習。 \r\n鼓勵學生閱讀活動，家長志工認真投入閱讀教學，提升學生語文程度。 \r\n重視天文教學，成立星象館、教學輔導園供師生研究教學。 \r\n提升學生潛能，設立安南區特教輔導中心服務安南區身心障礙兒童及家長。 \r\n用心打造新校園，規劃學習環境、柔美色調校舍，充實專科教室。 \r\n提倡重視生命教育與生態教育，成立蝴蝶園、生態教學區，加強環保意識。 \r\n推展體育活動，增進學生體適能與運動動機，長期組訓棒球(重點學校)、籃球、溜冰、跆拳道、巧固球等團隊，每年並定期舉辦校內路跑賽、溜冰賽、跆拳道賽、游泳賽、躲避球賽等。 \r\n推動音樂教育，涵養學生人文藝術素養，成立國樂班、直笛隊、合唱團，每年並定期舉辦校內鋼琴、直笛、歌唱等音樂比賽。 \r\n推展健康促進與衛教環保活動，教育部核定為廢乾電池回收、體控班、視力保健等重點學校。",
    "大事紀": "●70年 \r\n   ※5月10日林金水先生兼任本校籌備處主任。 \r\n   ※8月1日成立海東國小，安慶分校由鄒馥媛女士為安慶分校主任。 \r\n   ※10月15日安慶分校第一期校舍工程開工奠基典禮，由市長蘇南成先生\r\n        親臨主持。 \r\n●71年 \r\n   ※6月30日安慶分校第一期校舍工程，計地下室6間，教室6間，辦公室一\r\n        間，樓梯間2間，廁所一間，玄關等工程竣工。\r\n● 72年 \r\n    ※安慶分校學童由海東、安順國小遷回本校就讀，計10班。 \r\n    ※安慶分校第二期校舍工程計教室12間，校長室、音樂教室各一間竣\r\n        工。 \r\n    ※8月1日安慶分校正式獨立改為臺南市安南區安慶國民小學。 \r\n● 73年 \r\n    ※午餐供應開始，由市府撥資充實廚房設備。 \r\n● 74年 \r\n    ※田徑場、綜合球場、午餐儲藏室完工。 \r\n    ※6年國健專科教室、輔導室、地下室各一間，工程竣工。 \r\n● 76年 \r\n    ※南棟教室\\fs28 7間工程竣工。 \r\n● 77年 \r\n    ※獲選為禮貌運動推行績優學校。 \r\n    ※獲頒體育績優學校。 \r\n    ※獲全省教育部獎。 \r\n● 78年 \r\n    ※教室基礎補強7間工程竣工。 \r\n    ※成立圖書室、音樂教室、啟智班。 \r\n● 79年\r\n    ※專科教室7間工程竣工。 \r\n    ※舉辦國小數學科課程實驗研究觀摩教學。 \r\n    ※獲選為環保競賽績優學校。 \r\n    ※獲評為推行民主法治活動績優學校。 \r\n    ※成立星象館。 \r\n● 80年 \r\n    ※各處辦公室及專科教室8間工程竣工。 \r\n● 81年 \r\n    ※南北通廊工程竣工。 \r\n● 82年\r\n    ※興建各種專科教室和圖書室計24間。 \r\n    ※興建速維龍跑道。 \r\n● 83年 \r\n    ※積極籌組各類學生社團，培養學生正當興趣。 \r\n●85年 \r\n   ※陳金智校長8月接篆視事。\r\n   ※棒球隊成立。 \r\n●87年 \r\n   ※陳金智校長榮退，由教務主任黃朝源於2月1日起代理校長職務。\r\n   ※8月19日由新任校長謝銘澤接篆視事。\r\n   ※本校棒球隊赴日交流訪問做好國民外交。\r\n●88年 \r\n   ※本校推展開放教育，小班教學之推動。\r\n   ※繼續推展成人識字班推廣教育。\r\n   ※推廣班級電腦教學，發展資訊教育。\r\n●89年 \r\n   ※全校推展主題探索工作。\r\n   ※推展藝文性活動。\r\n   ※推動九年一貫實驗課程。\r\n●90年 \r\n   ※九年一貫教育正式實施。\r\n\r\n●91年 \r\n   ※8月1日新舊任校長交接,由新任校長吳榮煌接篆視事。\r\n   ※九年一貫課程正式推展第二年。\r\n   ※本校續推展晨間英語教學。\r\n   ※本校總體課表以維護愛惜生命為主題。\r\n   ※91年11月第三間電腦教室成立\r\n●92年 \r\n   ※試辦教、訓、輔三合一方案\r\n   ※成立安南區特教中心      \r\n   ※辦理廿週年校慶      \r\n   ※教材準備室建置\r\n●93年   \r\n   ※圖書館圖書電腦化建置    \r\n   ※全校網路化建置\r\n●94年\r\n   ※班班有電腦建置完成     \r\n   ※幼稚園增設全日班一班\r\n●95年\r\n   ※廚房、風雨球場改建工程完成設計工作  \r\n   ※加入教育部資訊夥伴學校\r\n \r\n \r\n\r\n\r\n\r\n\r\n\r\n\r\n\r\n項次\r\n\r\n日期\r\n\r\n內容\r\n\r\n備註\r\n\r\n\r\n          1        \r\n\r\n94年\r\n\r\n※ 班班有電腦建置完成 \r\n※ 幼稚園增設全日班一班\r\n\r\n \r\n\r\n\r\n          2        \r\n\r\n 95年\r\n\r\n※ 廚房、風雨球場改建工程完成設計工作  \r\n ※ 加入教育部資訊夥伴學\r\n※ 學校增設學前巡迴班，增特教一班  \r\n※ 吳榮煌校長連任\r\n\r\n \r\n\r\n\r\n          3        \r\n\r\n96年\r\n\r\n※ 廚房、風雨球場改建工程完工  \r\n ※ 同安路規劃「好望角」工程\r\n\r\n \r\n\r\n\r\n          4        \r\n\r\n97年\r\n\r\n※ 規劃大安街「好望角」工程   ※ 安慶少棒隊榮獲小馬聯盟世界盃亞軍 \r\n\r\n \r\n\r\n\r\n          5        \r\n\r\n98年\r\n\r\n※ 幼稚園增設全日班一班\r\n※ 大安接「邁向理想」好望角完工\r\n\r\n \r\n\r\n\r\n          6        \r\n\r\n100.6.22\r\n\r\nA東棟等七棟教室初步評估報告完成，七棟校舍(A東、A西、B、C東、C西、D、E棟)評估結果均為”應有疑慮”。\r\n\r\n承辦：弘基工程技術顧問股份有限公司\r\n\r\n\r\n          7        \r\n\r\n100.9.15\r\n\r\n市府核定補助A西、B棟詳評932,496元(100.9.15南市教小(一)字第1000694314號函)\r\n\r\n以「100年度安慶國小耐震能力詳細評估委託技術服務」辦理勞務採購，100.12.15評審完竣，由統勝工程顧問有限公司獲得優先議價權。\r\n\r\n\r\n          8        \r\n\r\n100.11.23\r\n\r\n郭市議員清華於議會審議教育局預算，關心校舍安全問題。議會決議教育小組擇期會勘。\r\n\r\n \r\n\r\n\r\n          9        \r\n\r\n100.12.19\r\n\r\n台南市議會教育委員會教育小組蒞校會勘。\r\n\r\n考察結論有二：一、針對安慶國小因土壤液化、地基掏空而造成校舍安全問題，請教育局儘速研擬對策，如有必要應遷校。二、請教育局一個月內會同都發局、地政局等相關局處重新進行地質調查，並將議員提出的遷校建議方案列入考量，向本會提出具體評估報告。(台南市議會100.12.20.南議教育字第1000011571A號函）\r\n\r\n\r\n        10      \r\n\r\n100.12.28\r\n\r\n函請市府同意停止校舍耐震詳細評估勞務採購案\r\n \r\n\r\n市議會教育小組蒞校勘查會議作成同意重建及市府應提規劃方案指示，本校亦經黃副局長旭信當場指示取消與廠商議價。\r\n（100.12.28南安慶總字第1000004833號函）\r\n\r\n\r\n        11      \r\n\r\n100.12.28\r\n\r\n函報市府申請操場地質調查經費需求\r\n\r\n100.12.28南安慶總字第1000004842號函。新臺幣9萬5970元。\r\n\r\n\r\n        12      \r\n\r\n101.1.9\r\n\r\n操場地質會同調查\r\n\r\n教育小組、本校、市府工務、都發、地政、教育局代表\r\n\r\n\r\n        13      \r\n\r\n101.1.11\r\n\r\n核定補助操場地質調查經費9萬5970元。\r\n\r\n台南市政府教育局101.1.11南市教小(一)字第1010037681號函\r\n\r\n\r\n        14      \r\n\r\n101.1.17\r\n\r\n市長蒞校視察校舍安全，召開會議。\r\n\r\n出席：市議會教育委員會教育小組、市府各局處代表、學區里長、本校校長、家長會長。\r\n賴市長清德作成三項結論(指裁示)：一、今天臺南市政府以具體行動宣示重建安慶國小校舍的決心；二、本案就地重建即刻啟動；三、安全問題輕忽不得，請學校提供就地重建簡單易懂的說帖，讓家長了解，以安定人心。(詳附件)\r\n\r\n\r\n        15      \r\n\r\n101.3.16\r\n\r\n市府函本校續辦建物耐震詳評\r\n\r\n101.3.16南市教小(一)字第1010218981號函\r\n\r\n\r\n        16      \r\n\r\n101.3.19\r\n\r\n陳報操場地質調查結果結論\r\n\r\n101.3.19安慶小總字第1010000984號函。地質調查結果填重點摘要：1地質鑽探結果顯示地表下0～1.7M屬於回層，1.7M～13.6M屬於軟弱土層。2.由液化潛能評估結果，本基地於地表下20公尺內之土層液化潛能較高，地層有液化疑慮。3.重建後的校舍基礎型式建議採用基樁基礎。\r\n結論：充份考慮地質條件與基礎型式，經由現代化之工程技術均可保證校舍不會有下陷的情形發生，本校校舍可就地重建。(詳附件)\r\n\r\n\r\n        17      \r\n\r\n101.3.29\r\n\r\n「100年度安慶國小耐震能力詳細評估委託技術服務」辦理議價完成。廠商統勝工程顧問有限公司以底價(73萬5000元)承攬。\r\n\r\n \r\n\r\n\r\n        18      \r\n\r\n101.4.13\r\n\r\n「100年度安慶國小耐震能力詳細評估委託技術服務」勞務採購簽約。\r\n\r\n \r\n\r\n\r\n        19      \r\n\r\n101.5.9\r\n\r\n「100年度安慶國小耐震能力詳細評估委託技術服務」期初報告審查會議\r\n\r\n \r\n\r\n\r\n        20      \r\n\r\n101.5.18\r\n\r\n教育部核定補助本校A東、C東、C西棟三棟教室詳評經費155萬9565元。\r\n\r\n教育部101.5.14臺國(一)字第1010076734號函；臺南市政府教育局101.5.18南市教小(一)字第1010409531號函。\r\n\r\n\r\n        21      \r\n\r\n101.6.6\r\n\r\n「100年度安慶國小耐震能力詳細評估委託技術服務」期末報告審查會議，審查通過。\r\n\r\n依評審委員意見修正，於101.6.26完成報告書定稿本。\r\n\r\n\r\n        22      \r\n\r\n101.6.26\r\n\r\n「101 年度安慶國小Ａ東、Ｃ東、Ｃ西棟教室耐震能力詳細評估委託技術服務」勞務採購，採共同契約方式辦理。\r\n\r\n與高雄市結構工程工業技師公會簽約。\r\n\r\n\r\n23\r\n\r\n101.7.16\r\n\r\n「101 年度安慶國小Ａ東、Ｃ東、Ｃ西棟教室耐震能力詳細評估委託技術服務」期初審查會議。\r\n\r\n \r\n\r\n\r\n24\r\n\r\n101.8.13\r\n\r\n「101 年度安慶國小Ａ東、Ｃ東、Ｃ西棟教室耐震能力詳細評估委託技術服務」期末審查會議。\r\n\r\n依評審委員意見修正，於101.8.27完成報告書定稿本",
    "校務未來發展重點": "秉持教育理念，提升學生學習潛能，針對國民教育五育均衡之發展。 \r\n充實教學設備，增添教學資源，改進教學方法以提升教學效能。 \r\n加強輔導工作，以因材施教為核心，有教無類為方針，促進學生身心均衡發展。 \r\n積極充實學校軟硬體建設，營造健康安全節能省碳活力新校園。 \r\n推展健康促進活動，提升學校親師生體適能，建立快樂活潑學習環境。"
}